py_templater/__init__.py
py_templater/__main__.py
py_templater-0.1.10.dist-info/LICENSE
py_templater-0.1.10.dist-info/METADATA
py_templater-0.1.10.dist-info/WHEEL
py_templater-0.1.10.dist-info/entry_points.txt
py_templater-0.1.10.dist-info/top_level.txt
py_templater-0.1.10.dist-info/RECORD
