Metadata-Version: 2.1
Name: py-templater
Version: 0.1.10
Summary: utility tool that generates code files from user-defined templates
Home-page: https://github.com/h3x4g0ns/py-templater/tree/master
Author: Ekansh Agrawal
Author-email: agrawalekansh@berkeley.edu
Keywords: python,template,cli
Classifier: Programming Language :: Python :: 3
Classifier: License :: OSI Approved :: MIT License
Classifier: Operating System :: OS Independent
Requires-Python: >=3.7
License-File: LICENSE
Requires-Dist: typer
Requires-Dist: rich
